konnyaku/__init__.py
konnyaku/__main__.py
konnyaku/bangumi.py
konnyaku/config.py
konnyaku/errors.py
konnyaku/llm.py
konnyaku/subs.py
konnyaku/translator.py
konnyaku/utils.py
konnyaku-1.0.4.dist-info/entry_points.txt
konnyaku-1.0.4.dist-info/LICENSE
konnyaku-1.0.4.dist-info/METADATA
konnyaku-1.0.4.dist-info/WHEEL
konnyaku-1.0.4.dist-info/RECORD
